ovmm/__init__.py
ovmm/cli.py
ovmm/commands/__init__.py
ovmm/commands/add_user.py
ovmm/commands/backup_user.py
ovmm/commands/count_user.py
ovmm/commands/delete_user.py
ovmm/commands/initialise.py
ovmm/commands/list_user.py
ovmm/commands/route_port.py
ovmm/config/__init__.py
ovmm/config/settings.py
ovmm/handlers/__init__.py
ovmm/handlers/nginx.py
ovmm/handlers/postgres.py
ovmm/handlers/samba.py
ovmm/prompts/__init__.py
ovmm/prompts/defaults.py
ovmm/prompts/parsers.py
ovmm/static/.profile
ovmm/static/exp_env.7z
ovmm/static/nginx_default_template
ovmm/static/nginx_template
ovmm/static/otree_environ_config
ovmm/static/ovmm_conf.yml
ovmm-0.2.2.dist-info/DESCRIPTION.rst
ovmm-0.2.2.dist-info/METADATA
ovmm-0.2.2.dist-info/RECORD
ovmm-0.2.2.dist-info/WHEEL
ovmm-0.2.2.dist-info/entry_points.txt
ovmm-0.2.2.dist-info/metadata.json
ovmm-0.2.2.dist-info/top_level.txt
