Metadata-Version: 2.0
Name: ovmm
Version: 0.2.2
Summary: ovmm manages your virtual machine for oTree.
Home-page: https://github.com/tobiasraabe/otree_virtual_machine_manager
Author: Tobias Raabe
Author-email: tobiasraabe@uni-bonn.de
License: MIT license
Keywords: ovmm
Platform: UNKNOWN
Classifier: Development Status :: 2 - Pre-Alpha
Classifier: Intended Audience :: Science/Research
Classifier: License :: OSI Approved :: MIT License
Classifier: Natural Language :: English
Classifier: Programming Language :: Python :: 3.4
Classifier: Programming Language :: Python :: 3.5
Classifier: Programming Language :: Python :: 3.6
Requires-Dist: Click (>=6.0)
Requires-Dist: PyYAML (>=3.12)
Requires-Dist: plumbum (>=1.6.3)
Requires-Dist: psycopg2 (>=2.6.2)
